{
  "task": "repair_discord_architect_salvage_zero_quarantine_001",
  "status": "PASS",
  "repair": "zero quarantined roots accepted because only retained source/test candidates remain",
  "manifest": "runtime/quarantine/discord_architect_artifacts_001/manifest.json",
  "manifest_summary": {
    "source_candidate_files_retained": 2,
    "quarantined_roots": 0,
    "quarantined_files": 0,
    "retained_roots": 2,
    "missing_roots": 6
  },
  "retained_files": [
    "discord_architect/src/runtime/channelWebhookManager.js",
    "discord_architect/tests/channelWebhookManager.test.js"
  ],
  "source_status": [
    "?? discord_architect/src/",
    "?? discord_architect/tests/"
  ],
  "decision": {
    "quarantine_required": false,
    "reason": "classification roots were already missing or previously moved; current actionable residue is retained source/test candidate review",
    "next_lane": "inspect_discord_architect_source_candidates_001"
  },
  "next_lane": "inspect_discord_architect_source_candidates_001"
}
